aspsim/__init__.py
aspsim/array.py
aspsim/config.yaml
aspsim/configutil.py
aspsim/counter.py
aspsim/fileutilities.py
aspsim/processor.py
aspsim/saveloadsession.py
aspsim/simulator.py
aspsim/utilities.py
aspsim/diagnostics/core.py
aspsim/diagnostics/diagnostics.py
aspsim/diagnostics/diagnosticscollection.py
aspsim/diagnostics/diagnosticsummary.py
aspsim/diagnostics/plot.py
aspsim/diagnostics/preprocessing.py
aspsim/diagnostics/soundfieldplot.py
aspsim/room/__init__.py
aspsim/room/directional.py
aspsim/room/generatepoints.py
aspsim/room/region.py
aspsim/room/roomimpulseresponse.py
aspsim/room/trajectory.py
aspsim/signal/__init__.py
aspsim/signal/sources.py
aspsim-0.0.2.dist-info/licenses/LICENSE
aspsim-0.0.2.dist-info/METADATA
aspsim-0.0.2.dist-info/WHEEL
aspsim-0.0.2.dist-info/top_level.txt
aspsim-0.0.2.dist-info/RECORD
