Metadata-Version: 2.4
Name: aspsim
Version: 0.0.2
Author-email: Jesper Brunnström <jesper_brunnstrom@hotmail.com>
Project-URL: Documentation, https://sounds-research.github.io/aspsim/
Project-URL: Repository, https://github.com/SOUNDS-RESEARCH/aspsim
Classifier: Operating System :: OS Independent
Classifier: Programming Language :: Python :: 3
Classifier: License :: OSI Approved :: MIT License
Requires-Python: >=3.11
License-File: LICENSE
Requires-Dist: numpy
Requires-Dist: scipy
Requires-Dist: matplotlib
Requires-Dist: dill
Requires-Dist: pyyaml
Requires-Dist: soundfile
Requires-Dist: pyroomacoustics
Requires-Dist: aspcore
Provides-Extra: test
Requires-Dist: pytest; extra == "test"
Requires-Dist: hypothesis; extra == "test"
Dynamic: license-file
